{
    "key": "group_6085b01e0cc0d",
    "title": "Block - Basic Content",
    "fields": [
        {
            "key": "field_6085b09b9d91b",
            "label": "Alignment",
            "name": "alignment",
            "type": "button_group",
            "instructions": "",
            "required": 0,
            "conditional_logic": 0,
            "wrapper": {
                "width": "",
                "class": "",
                "id": ""
            },
            "choices": {
                "align-left": "Left",
                "align-center": "Center",
                "align-right": "Right"
            },
            "allow_null": 0,
            "default_value": "align-left",
            "layout": "horizontal",
            "return_format": "value"
        },
        {
            "key": "field_6085b02e9d918",
            "label": "Intro",
            "name": "intro",
            "type": "clone",
            "instructions": "",
            "required": 0,
            "conditional_logic": 0,
            "wrapper": {
                "width": "",
                "class": "",
                "id": ""
            },
            "clone": [
                "group_6085adfcd7186"
            ],
            "display": "seamless",
            "layout": "block",
            "prefix_label": 0,
            "prefix_name": 0
        },
        {
            "key": "field_6085b0529d919",
            "label": "Content",
            "name": "content",
            "type": "wysiwyg",
            "instructions": "",
            "required": 0,
            "conditional_logic": 0,
            "wrapper": {
                "width": "",
                "class": "",
                "id": ""
            },
            "default_value": "",
            "tabs": "all",
            "toolbar": "full",
            "media_upload": 1,
            "delay": 0
        },
        {
            "key": "field_6085b0859d91a",
            "label": "Buttons",
            "name": "buttons",
            "type": "clone",
            "instructions": "",
            "required": 0,
            "conditional_logic": 0,
            "wrapper": {
                "width": "",
                "class": "",
                "id": ""
            },
            "clone": [
                "group_6085ad62e4e74"
            ],
            "display": "seamless",
            "layout": "block",
            "prefix_label": 0,
            "prefix_name": 0
        }
    ],
    "location": [
        [
            {
                "param": "post_type",
                "operator": "==",
                "value": "post"
            }
        ]
    ],
    "menu_order": 0,
    "position": "normal",
    "style": "default",
    "label_placement": "top",
    "instruction_placement": "label",
    "hide_on_screen": "",
    "active": false,
    "description": "",
    "modified": 1619374394
}